stamped_and_sealed/__init__.py
stamped_and_sealed/dev_compliments.py
stamped_and_sealed/fortune_py.py
stamped_and_sealed/leetspeak.py
stamped_and_sealed/reverse_text.py
stamped_and_sealed-0.1.0.dist-info/licenses/LICENSE
stamped_and_sealed-0.1.0.dist-info/METADATA
stamped_and_sealed-0.1.0.dist-info/WHEEL
stamped_and_sealed-0.1.0.dist-info/top_level.txt
stamped_and_sealed-0.1.0.dist-info/RECORD
