Metadata-Version: 2.4
Name: stamped_and_sealed
Version: 0.1.0
Summary: A fun Python package for developers
Author-email: Your Team <team@example.com>
License-File: LICENSE
Dynamic: license-file
